setup.py
tinystomp.py
tinystomp.egg-info/PKG-INFO
tinystomp.egg-info/SOURCES.txt
tinystomp.egg-info/dependency_links.txt
tinystomp.egg-info/top_level.txt