Metadata-Version: 1.0
Name: tinystomp
Version: 0.0.0
Summary: Ultra minimal STOMP protocol parser
Home-page: http://github.com/dw/tinystomp/
Author: David Wilson
Author-email: dw@botanicus.net
License: Apache 2
Platform: UNKNOWN
